dbbasic_web/__init__.py
dbbasic_web/asgi.py
dbbasic_web/bus.py
dbbasic_web/cli.py
dbbasic_web/jobs.py
dbbasic_web/request.py
dbbasic_web/responses.py
dbbasic_web/router.py
dbbasic_web/settings.py
dbbasic_web/sse.py
dbbasic_web/static.py
dbbasic_web/storage.py
dbbasic_web/templating.py
dbbasic_web/websocket.py
dbbasic_web/public/css/app.css
dbbasic_web/public/js/app.js
dbbasic_web/templates/base.html
dbbasic_web/templates/index.html
dbbasic_web-0.1.10.dist-info/licenses/LICENSE
dbbasic_web-0.1.10.dist-info/METADATA
dbbasic_web-0.1.10.dist-info/WHEEL
dbbasic_web-0.1.10.dist-info/entry_points.txt
dbbasic_web-0.1.10.dist-info/top_level.txt
dbbasic_web-0.1.10.dist-info/RECORD
