Metadata-Version: 2.4
Name: dbbasic-web
Version: 0.1.10
Summary: Unixy micro-framework: file routing, SSE/WS, jobs, bus, flat files.
Author-email: DBBasic Team <hello@dbbasic.com>
License: MIT
Project-URL: Homepage, https://dbbasic.com
Project-URL: Documentation, https://github.com/dbbasic/dbbasic-web
Project-URL: Repository, https://github.com/dbbasic/dbbasic-web
Project-URL: Issues, https://github.com/dbbasic/dbbasic-web/issues
Keywords: web,framework,cgi,unix,tsv,async,asgi
Classifier: Development Status :: 3 - Alpha
Classifier: Intended Audience :: Developers
Classifier: License :: OSI Approved :: MIT License
Classifier: Programming Language :: Python :: 3
Classifier: Programming Language :: Python :: 3.10
Classifier: Programming Language :: Python :: 3.11
Classifier: Programming Language :: Python :: 3.12
Classifier: Framework :: AsyncIO
Classifier: Topic :: Internet :: WWW/HTTP :: HTTP Servers
Classifier: Topic :: Internet :: WWW/HTTP :: WSGI :: Application
Classifier: Topic :: Software Development :: Libraries :: Application Frameworks
Requires-Python: >=3.10
License-File: LICENSE
Requires-Dist: uvicorn[standard]>=0.30.0
Requires-Dist: jinja2>=3.1.4
Requires-Dist: watchfiles>=0.21.0
Requires-Dist: python-multipart>=0.0.9
Requires-Dist: itsdangerous>=2.2.0
Requires-Dist: websockets>=12.0
Requires-Dist: dbbasic-tsv
Requires-Dist: dbbasic-queue
Requires-Dist: dbbasic-pipe
Requires-Dist: dbbasic-sessions
Dynamic: license-file
